moclust/__init__.py
moclust/config.py
moclust/ddc.py
moclust/evaluate.py
moclust/fusion.py
moclust/gene_matrix.py
moclust/helpers.py
moclust/loss.py
moclust/loss_kernels.py
moclust/model.py
moclust/multiview_autoencoders.py
moclust/optimizer.py
moclust/preprocess.py
moclust/train.py
moclust/utils.py
moclust-0.0.1.dist-info/LICENSE
moclust-0.0.1.dist-info/METADATA
moclust-0.0.1.dist-info/WHEEL
moclust-0.0.1.dist-info/top_level.txt
moclust-0.0.1.dist-info/RECORD
