Metadata-Version: 2.1
Name: moclust
Version: 0.0.1
Summary: A deep learning-based clustering method for single-cell multi-omics data
Home-page: https://github.com/ddb-qiwang/MoClust
Author: yuanmusu
Author-email: yuanmusu@pku.edu.cn
Classifier: Programming Language :: Python :: 3
Classifier: License :: OSI Approved :: MIT License
Classifier: Operating System :: OS Independent
Requires-Python: >=3.6
License-File: LICENSE
Requires-Dist: scanpy (>=1.6.0)
Requires-Dist: numpy (>=1.21.6)
Requires-Dist: pandas (>=1.3.5)
Requires-Dist: torch (==1.10.2)
Requires-Dist: scikit-learn (>=1.0.2)
Requires-Dist: scipy (>=1.4.1)
Requires-Dist: seaborn (>=0.9.0)
Requires-Dist: tabulate (==0.8.9)
Requires-Dist: pydantic (==1.10.2)
Requires-Dist: typing (>=3.5.0)
